LICENSE
README.md
setup.py
pyOrbitenc/__init__.py
pyOrbitenc/pyOrbitenc.py
pyOrbitenc.egg-info/PKG-INFO
pyOrbitenc.egg-info/SOURCES.txt
pyOrbitenc.egg-info/dependency_links.txt
pyOrbitenc.egg-info/not-zip-safe
pyOrbitenc.egg-info/top_level.txt