Metadata-Version: 2.1
Name: pyOrbitenc
Version: 1.6
Summary: A Powerfull Encryptor For Encrypting Python Script. It Has No Decode Function. It Directly Execute Your Encrypted Code
Home-page: https://pypi.org/project/pyOrbitenc
Download-URL: https://pypi.org/project/pyOrbitenc
Author: cracker911181
Author-email: admin@cracker911181.cf
License: MIT
License-File: LICENSE
